<FBType Comment="Basic FB with empty ECC" Name="Basic">
  <Identification Standard="61499-2" />
  <VersionInfo Author="AZ" Date="2016-05-26" Organization="fortiss GmbH" Version="1.0" />
  <InterfaceList>
    <EventInputs>  
    <Event Comment="" Name="CU" Type="Event" /><Event Comment="" Name="R" Type="Event" /></EventInputs>
    <EventOutputs>
    <Event Comment="" Name="CUO" Type="Event" /><Event Comment="" Name="RO" Type="Event" /></EventOutputs>
    <InputVars>
    </InputVars>
    <OutputVars>
    <VarDeclaration Comment="" Name="PV" Type="BOOL" /><VarDeclaration Comment="" Name="Q" Type="BOOL" /><VarDeclaration Comment="" Name="CV" Type="BOOL" /></OutputVars>
  </InterfaceList>
  <BasicFB>
    <ECC>
    <ECState Comment="" Name="START" /><ECState Comment="" Name="R"><ECAction Algorithm="R" Output="RO" /></ECState><ECState Comment="" Name="CU"><ECAction Algorithm="CU" Output="CUO" /></ECState><ECTransition Comment="" Condition="CU[CV &lt; 65535]" Destination="CU" Source="START" /><ECTransition Comment="" Condition="R" Destination="R" Source="START" /><ECTransition Comment="" Condition="1" Destination="START" Source="R" /><ECTransition Comment="" Condition="1" Destination="START" Source="CU" /></ECC>
  <Algorithm Comment="" Name="R"><ST Text="CV := 0;&#10;Q := FALSE;" /></Algorithm><Algorithm Comment="" Name="CU"><ST Text="CV := CV + 1;&#10;Q  := (CV &gt;= PV);" /></Algorithm></BasicFB>
</FBType>